<?xml version="1.0" encoding="UTF-8"?>
<abstract-citations-response xmlns:xocs="http://www.elsevier.com/xml/xocs/dtd" xmlns:ns2="http://webservices.elsevier.com/schemas/metadata/cto/types/v4" xmlns:ctom="http://www.elsevier.com/xml/ctom/dtd" xmlns:cto="http://www.elsevier.com/xml/cto/dtd" xmlns:prism="http://prismstandard.org/namespaces/basic/2.0/" xmlns:dc="http://purl.org/dc/elements/1.1/"><h-index>2</h-index><identifier-legend><identifier><dc:identifier>SCOPUS_ID:84939124377</dc:identifier><scopus_id>84939124377</scopus_id></identifier><identifier><dc:identifier>SCOPUS_ID:84938769733</dc:identifier><scopus_id>84938769733</scopus_id></identifier><identifier><dc:identifier>SCOPUS_ID:84938770947</dc:identifier><scopus_id>84938770947</scopus_id></identifier><identifier><dc:identifier>SCOPUS_ID:84938802206</dc:identifier><scopus_id>84938802206</scopus_id></identifier><identifier><dc:identifier>SCOPUS_ID:84938818292</dc:identifier><scopus_id>84938818292</scopus_id></identifier><identifier><dc:identifier>SCOPUS_ID:84934344109</dc:identifier><scopus_id>84934344109</scopus_id></identifier><identifier><dc:identifier>SCOPUS_ID:84947285680</dc:identifier><scopus_id>84947285680</scopus_id></identifier><identifier><dc:identifier>SCOPUS_ID:85009771927</dc:identifier><scopus_id>85009771927</scopus_id></identifier><identifier><dc:identifier>SCOPUS_ID:84945959419</dc:identifier><scopus_id>84945959419</scopus_id></identifier><identifier><dc:identifier>SCOPUS_ID:84943666241</dc:identifier><scopus_id>84943666241</scopus_id></identifier></identifier-legend><citeInfoMatrix><citeInfoMatrixXML><citationMatrix xmlns="http://www.elsevier.com/xml/ctom/dtd"><citeInfo xmlns=""><dc:identifier>SCOPUS_ID:84939124377</dc:identifier><sort-year>2015</sort-year><pcc>0</pcc><cc>0</cc><cc>0</cc><cc>0</cc><cc>0</cc><cc>0</cc><cc>0</cc><cc>0</cc><cc>0</cc><cc>0</cc><cc>0</cc><cc>1</cc><cc>1</cc><lcc>0</lcc><rangeCount>2</rangeCount><rowTotal>2</rowTotal></citeInfo><citeInfo xmlns=""><dc:identifier>SCOPUS_ID:84938769733</dc:identifier><sort-year>2015</sort-year><pcc>0</pcc><cc>0</cc><cc>0</cc><cc>0</cc><cc>0</cc><cc>0</cc><cc>0</cc><cc>0</cc><cc>0</cc><cc>0</cc><cc>0</cc><cc>0</cc><cc>0</cc><lcc>0</lcc><rangeCount>0</rangeCount><rowTotal>0</rowTotal></citeInfo><citeInfo xmlns=""><dc:identifier>SCOPUS_ID:84938770947</dc:identifier><sort-year>2015</sort-year><pcc>0</pcc><cc>0</cc><cc>0</cc><cc>0</cc><cc>0</cc><cc>0</cc><cc>0</cc><cc>0</cc><cc>0</cc><cc>0</cc><cc>0</cc><cc>1</cc><cc>0</cc><lcc>0</lcc><rangeCount>1</rangeCount><rowTotal>1</rowTotal></citeInfo><citeInfo xmlns=""><dc:identifier>SCOPUS_ID:84938802206</dc:identifier><sort-year>2015</sort-year><pcc>0</pcc><cc>0</cc><cc>0</cc><cc>0</cc><cc>0</cc><cc>0</cc><cc>0</cc><cc>0</cc><cc>0</cc><cc>0</cc><cc>0</cc><cc>0</cc><cc>0</cc><lcc>0</lcc><rangeCount>0</rangeCount><rowTotal>0</rowTotal></citeInfo><citeInfo xmlns=""><dc:identifier>SCOPUS_ID:84938818292</dc:identifier><sort-year>2015</sort-year><pcc>0</pcc><cc>0</cc><cc>0</cc><cc>0</cc><cc>0</cc><cc>0</cc><cc>0</cc><cc>0</cc><cc>0</cc><cc>0</cc><cc>0</cc><cc>1</cc><cc>0</cc><lcc>0</lcc><rangeCount>1</rangeCount><rowTotal>1</rowTotal></citeInfo><citeInfo xmlns=""><dc:identifier>SCOPUS_ID:84934344109</dc:identifier><sort-year>2015</sort-year><pcc>0</pcc><cc>0</cc><cc>0</cc><cc>0</cc><cc>0</cc><cc>0</cc><cc>0</cc><cc>0</cc><cc>0</cc><cc>0</cc><cc>0</cc><cc>2</cc><cc>0</cc><lcc>0</lcc><rangeCount>2</rangeCount><rowTotal>2</rowTotal></citeInfo><citeInfo xmlns=""><dc:identifier>SCOPUS_ID:84947285680</dc:identifier><sort-year>2015</sort-year><pcc>0</pcc><cc>0</cc><cc>0</cc><cc>0</cc><cc>0</cc><cc>0</cc><cc>0</cc><cc>0</cc><cc>0</cc><cc>0</cc><cc>0</cc><cc>0</cc><cc>0</cc><lcc>0</lcc><rangeCount>0</rangeCount><rowTotal>0</rowTotal></citeInfo><citeInfo xmlns=""><dc:identifier>SCOPUS_ID:85009771927</dc:identifier><sort-year>2015</sort-year><pcc>0</pcc><cc>0</cc><cc>0</cc><cc>0</cc><cc>0</cc><cc>0</cc><cc>0</cc><cc>0</cc><cc>0</cc><cc>0</cc><cc>0</cc><cc>0</cc><cc>0</cc><lcc>0</lcc><rangeCount>0</rangeCount><rowTotal>0</rowTotal></citeInfo><citeInfo xmlns=""><dc:identifier>SCOPUS_ID:84945959419</dc:identifier><sort-year>2015</sort-year><pcc>0</pcc><cc>0</cc><cc>0</cc><cc>0</cc><cc>0</cc><cc>0</cc><cc>0</cc><cc>0</cc><cc>0</cc><cc>0</cc><cc>0</cc><cc>1</cc><cc>0</cc><lcc>0</lcc><rangeCount>1</rangeCount><rowTotal>1</rowTotal></citeInfo><citeInfo xmlns=""><dc:identifier>SCOPUS_ID:84943666241</dc:identifier><sort-year>2015</sort-year><pcc>0</pcc><cc>0</cc><cc>0</cc><cc>0</cc><cc>0</cc><cc>0</cc><cc>0</cc><cc>0</cc><cc>0</cc><cc>0</cc><cc>0</cc><cc>0</cc><cc>1</cc><lcc>0</lcc><rangeCount>1</rangeCount><rowTotal>1</rowTotal></citeInfo></citationMatrix></citeInfoMatrixXML></citeInfoMatrix><citeColumnTotalXML><citeCountHeader><prevColumnHeading>previous</prevColumnHeading><columnHeading>2006</columnHeading><columnHeading>2007</columnHeading><columnHeading>2008</columnHeading><columnHeading>2009</columnHeading><columnHeading>2010</columnHeading><columnHeading>2011</columnHeading><columnHeading>2012</columnHeading><columnHeading>2013</columnHeading><columnHeading>2014</columnHeading><columnHeading>2015</columnHeading><columnHeading>2016</columnHeading><columnHeading>2017</columnHeading><laterColumnHeading>later</laterColumnHeading><prevColumnTotal>0</prevColumnTotal><columnTotal>0</columnTotal><columnTotal>0</columnTotal><columnTotal>0</columnTotal><columnTotal>0</columnTotal><columnTotal>0</columnTotal><columnTotal>0</columnTotal><columnTotal>0</columnTotal><columnTotal>0</columnTotal><columnTotal>0</columnTotal><columnTotal>0</columnTotal><columnTotal>6</columnTotal><columnTotal>2</columnTotal><laterColumnTotal>0</laterColumnTotal><rangeColumnTotal>8</rangeColumnTotal></citeCountHeader></citeColumnTotalXML></abstract-citations-response>