<?xml version="1.0" encoding="UTF-8"?>
<abstracts-retrieval-response xmlns="http://www.elsevier.com/xml/svapi/abstract/dtd" xmlns:ait="http://www.elsevier.com/xml/ani/ait" xmlns:ce="http://www.elsevier.com/xml/ani/common" xmlns:cto="http://www.elsevier.com/xml/cto/dtd" xmlns:dc="http://purl.org/dc/elements/1.1/" xmlns:prism="http://prismstandard.org/namespaces/basic/2.0/" xmlns:xocs="http://www.elsevier.com/xml/xocs/dtd" xmlns:xsi="http://www.w3.org/2001/XMLSchema-instance">
  <coredata>
    <prism:url>http://api.elsevier.com/content/abstract/scopus_id/84979796578</prism:url>
    <dc:identifier>SCOPUS_ID:84979796578</dc:identifier>
    <eid>2-s2.0-84979796578</eid>
    <dc:title>Effectiveness of an Assertive Community Treatment Program for patients with severe mental disorder</dc:title>
    <prism:aggregationType>Journal</prism:aggregationType>
    <srctype>j</srctype>
    <citedby-count>0</citedby-count>
    <prism:publicationName>Revista de Psicopatologia y Psicologia Clinica</prism:publicationName>
    <dc:publisher> Asoc. Espanola de Psicologia Clinica y Psicopatologia aepcp@aepcp.net </dc:publisher>
    <source-id>21100200812</source-id>
    <prism:issn>11365420</prism:issn>
    <prism:volume>17</prism:volume>
    <prism:issueIdentifier>1</prism:issueIdentifier>
    <prism:startingPage>1</prism:startingPage>
    <prism:endingPage>10</prism:endingPage>
    <prism:pageRange>1-10</prism:pageRange>
    <prism:coverDate>2012-01-01</prism:coverDate>
    <dc:creator>
      <author auid="57190407735" seq="1">
        <ce:initials>J.</ce:initials>
        <ce:indexed-name>Lopez-Santiago J.</ce:indexed-name>
        <ce:surname>López-Santiago</ce:surname>
        <ce:given-name>José</ce:given-name>
        <preferred-name> <ce:initials>J.</ce:initials> <ce:indexed-name>López-Santiago J.</ce:indexed-name> <ce:surname>López-Santiago</ce:surname> <ce:given-name>José</ce:given-name> </preferred-name>
        <author-url>http://api.elsevier.com/content/author/author_id/57190407735</author-url>
        <affiliation href="http://api.elsevier.com/content/affiliation/affiliation_id/60012044" id="60012044"/>
      </author>
    </dc:creator>
    <dc:description>
      <abstract original="y" xml:lang="eng"> <ce:para>The Program for Assertive Community Treatment in Albacete (Spain) is a multidisci-plinary team effort directed at the care for patients with severe mental disorders. The aim of this work is to study its effectiveness in reducing hospital admissions and emergency care. Two pre-post tests were conducted, one at 12 months (N = 55) and the other at 36 months (N = 38). The differences found were significant in all cases. In the 12 months' study the number of admissions reduced from 83 to 28; the number of admitted days decreased from 1.494 to 252; and the number of emergencies dropped from 66 to 12. In the 36 months' study the results were similar, with a medium to large effect size in all cases. The number of patients admitted also dropped 64% and 43.33% respectively. The program, which is applied in a context of real life research, has shown to be effective. © Asociación Española de Psicología Clínica y Psicopatología.</ce:para> </abstract>
    </dc:description>
    <intid>84979796578</intid>
    <link href="http://api.elsevier.com/content/abstract/scopus_id/84979796578" rel="self"/>
    <link href="https://www.scopus.com/inward/record.uri?partnerID=HzOxMe3b&amp;scp=84979796578&amp;origin=inward" rel="scopus"/>
    <link href="https://www.scopus.com/inward/citedby.uri?partnerID=HzOxMe3b&amp;scp=84979796578&amp;origin=inward" rel="scopus-citedby"/>
  </coredata>
  <affiliation href="http://api.elsevier.com/content/affiliation/affiliation_id/60012044" id="60012044">
    <affilname>Hospital Perpetuo Socorro</affilname>
    <affiliation-city>Badajoz</affiliation-city>
    <affiliation-country>Spain</affiliation-country>
  </affiliation>
  <authors>
    <author auid="57190407735" seq="1">
      <ce:initials>J.</ce:initials>
      <ce:indexed-name>Lopez-Santiago J.</ce:indexed-name>
      <ce:surname>López-Santiago</ce:surname>
      <ce:given-name>José</ce:given-name>
      <preferred-name> <ce:initials>J.</ce:initials> <ce:indexed-name>López-Santiago J.</ce:indexed-name> <ce:surname>López-Santiago</ce:surname> <ce:given-name>José</ce:given-name> </preferred-name>
      <author-url>http://api.elsevier.com/content/author/author_id/57190407735</author-url>
      <affiliation href="http://api.elsevier.com/content/affiliation/affiliation_id/60012044" id="60012044"/>
    </author>
    <author auid="57190408760" seq="2">
      <ce:initials>L.V.</ce:initials>
      <ce:indexed-name>Blas L.V.</ce:indexed-name>
      <ce:surname>Blas</ce:surname>
      <ce:given-name>Luis V.</ce:given-name>
      <preferred-name> <ce:initials>L.V.</ce:initials> <ce:indexed-name>Blas L.</ce:indexed-name> <ce:surname>Blas</ce:surname> <ce:given-name>Luis V.</ce:given-name> </preferred-name>
      <author-url>http://api.elsevier.com/content/author/author_id/57190408760</author-url>
      <affiliation href="http://api.elsevier.com/content/affiliation/affiliation_id/60012044" id="60012044"/>
    </author>
    <author auid="57190412496" seq="3">
      <ce:initials>M.</ce:initials>
      <ce:indexed-name>Gomez M.</ce:indexed-name>
      <ce:surname>Gómez</ce:surname>
      <ce:given-name>Mónica</ce:given-name>
      <preferred-name> <ce:initials>M.</ce:initials> <ce:indexed-name>Gómez M.</ce:indexed-name> <ce:surname>Gómez</ce:surname> <ce:given-name>Mónica</ce:given-name> </preferred-name>
      <author-url>http://api.elsevier.com/content/author/author_id/57190412496</author-url>
      <affiliation href="http://api.elsevier.com/content/affiliation/affiliation_id/60012044" id="60012044"/>
    </author>
  </authors>
  <language xml:lang="spa"/>
  <authkeywords>
    <author-keyword>Assertive Community Treatment</author-keyword>
    <author-keyword>Effectiveness</author-keyword>
    <author-keyword>Real-life research</author-keyword>
    <author-keyword>Severe mental disorder</author-keyword>
  </authkeywords>
  <idxterms/>
  <subject-areas>
    <subject-area abbrev="PSYC" code="3203">Clinical Psychology</subject-area>
    <subject-area abbrev="MEDI" code="2738">Psychiatry and Mental Health</subject-area>
  </subject-areas>
  <item xmlns="">
    <ait:process-info>
      <ait:date-delivered day="09" month="12" timestamp="2016-12-09T02:49:32.000032+00:00" year="2016"/>
      <ait:date-sort day="01" month="01" year="2012"/>
      <ait:status stage="S300" state="update" type="core"/>
    </ait:process-info>
    <bibrecord>
      <item-info>
        <copyright type="Elsevier">Copyright 2016 Elsevier B.V., All rights reserved.</copyright>
        <itemidlist> <itemid idtype="PUI">365843325</itemid> <itemid idtype="CAR-ID">310682360</itemid> <itemid idtype="SNPSYB">2012016403</itemid> <itemid idtype="SCP">84979796578</itemid> <itemid idtype="SGR">84979796578</itemid> </itemidlist>
        <history> <date-created day="24" month="11" timestamp="BST 14:45:12" year="2016"/> </history>
        <dbcollection>SNPSYB</dbcollection>
        <dbcollection>Scopusbase</dbcollection>
      </item-info>
      <head>
        <citation-info>
          <citation-type code="ar"/>
          <citation-language language="Spanish" xml:lang="spa"/>
          <abstract-language language="English" xml:lang="eng"/>
          <abstract-language language="Spanish" xml:lang="spa"/>
          <author-keywords> <author-keyword>Assertive Community Treatment</author-keyword> <author-keyword>Effectiveness</author-keyword> <author-keyword>Real-life research</author-keyword> <author-keyword>Severe mental disorder</author-keyword> </author-keywords>
        </citation-info>
        <citation-title>
          <titletext language="English" original="n" xml:lang="eng">Effectiveness of an Assertive Community Treatment Program for patients with severe mental disorder</titletext>
          <titletext language="Spanish" original="y" xml:lang="spa">Efectividad de un Programa de Tratamiento Asertivo Comunitario para pacientes con trastorno mental grave</titletext>
        </citation-title>
        <author-group>
          <author auid="57190407735" seq="1" type="auth"> <ce:initials>J.</ce:initials> <ce:indexed-name>Lopez-Santiago J.</ce:indexed-name> <ce:surname>López-Santiago</ce:surname> <ce:given-name>José</ce:given-name> <preferred-name> <ce:initials>J.</ce:initials> <ce:indexed-name>López-Santiago J.</ce:indexed-name> <ce:surname>López-Santiago</ce:surname> <ce:given-name>José</ce:given-name> </preferred-name> <ce:e-address type="email">jlopezs@sescam.jccm.es</ce:e-address> </author>
          <author auid="57190408760" seq="2" type="auth"> <ce:initials>L.V.</ce:initials> <ce:indexed-name>Blas L.V.</ce:indexed-name> <ce:surname>Blas</ce:surname> <ce:given-name>Luis V.</ce:given-name> <preferred-name> <ce:initials>L.V.</ce:initials> <ce:indexed-name>Blas L.</ce:indexed-name> <ce:surname>Blas</ce:surname> <ce:given-name>Luis V.</ce:given-name> </preferred-name> </author>
          <author auid="57190412496" seq="3" type="auth"> <ce:initials>M.</ce:initials> <ce:indexed-name>Gomez M.</ce:indexed-name> <ce:surname>Gómez</ce:surname> <ce:given-name>Mónica</ce:given-name> <preferred-name> <ce:initials>M.</ce:initials> <ce:indexed-name>Gómez M.</ce:indexed-name> <ce:surname>Gómez</ce:surname> <ce:given-name>Mónica</ce:given-name> </preferred-name> </author>
          <affiliation afid="60012044" country="esp" dptid="117686691">
            <organization>Servicio de Salud Mental</organization>
            <organization>Hospital Perpetuo Socorro</organization>
            <organization>Universitario de Albacete</organization>
            <address-part>Seminario 4</address-part>
            <city-group>02006 Albacete</city-group>
            <country>Spain</country>
          </affiliation>
        </author-group>
        <correspondence>
          <person> <ce:initials>J.</ce:initials> <ce:indexed-name>Lopez-Santiago J.</ce:indexed-name> <ce:surname>López-Santiago</ce:surname> </person>
          <affiliation country="esp">
            <organization>Servicio de Salud Mental</organization>
            <organization>Hospital Perpetuo Socorro</organization>
            <organization>Universitario de Albacete</organization>
            <address-part>Seminario 4</address-part>
            <city-group>02006 Albacete</city-group>
            <country>Spain</country>
          </affiliation>
          <ce:e-address type="email">jlopezs@sescam.jccm.es</ce:e-address>
        </correspondence>
        <abstracts>
          <abstract original="y" xml:lang="eng"> <ce:para>The Program for Assertive Community Treatment in Albacete (Spain) is a multidisci-plinary team effort directed at the care for patients with severe mental disorders. The aim of this work is to study its effectiveness in reducing hospital admissions and emergency care. Two pre-post tests were conducted, one at 12 months (N = 55) and the other at 36 months (N = 38). The differences found were significant in all cases. In the 12 months' study the number of admissions reduced from 83 to 28; the number of admitted days decreased from 1.494 to 252; and the number of emergencies dropped from 66 to 12. In the 36 months' study the results were similar, with a medium to large effect size in all cases. The number of patients admitted also dropped 64% and 43.33% respectively. The program, which is applied in a context of real life research, has shown to be effective. © Asociación Española de Psicología Clínica y Psicopatología.</ce:para> </abstract>
        </abstracts>
        <source country="esp" srcid="21100200812" type="j">
          <sourcetitle>Revista de Psicopatologia y Psicologia Clinica</sourcetitle>
          <sourcetitle-abbrev>Rev. Psicopatol. Psicol. Clin.</sourcetitle-abbrev>
          <translated-sourcetitle xml:lang="eng">Revista de Psicopatologia y Psicologia Clinica</translated-sourcetitle>
          <issn type="print">11365420</issn>
          <volisspag> <voliss issue="1" volume="17"/> <pagerange first="1" last="10"/> </volisspag>
          <publicationyear first="2012"/>
          <publicationdate> <year>2012</year> <date-text>April 2012</date-text> </publicationdate>
          <website> <ce:e-address type="email">http://www.aepcp.net/arc/01_2012_n1_lopez_blas_gomez.pdf</ce:e-address> </website>
          <publisher> <publishername>Asoc. Espanola de Psicologia Clinica y Psicopatologia</publishername> <ce:e-address type="email">aepcp@aepcp.net</ce:e-address> </publisher>
        </source>
        <enhancement>
          <classificationgroup>
            <classifications type="ASJC"> <classification>3203</classification> <classification>2738</classification> </classifications>
            <classifications type="SUBJABBR">
              <classification>PSYC</classification>
              <classification>MEDI</classification>
            </classifications>
          </classificationgroup>
        </enhancement>
      </head>
      <tail>
        <bibliography refcount="55"> <reference id="1"> <ref-info> <ref-title> <ref-titletext>Origen y desarrollo de los programas de seguimiento y cuidados para pacientes mentales graves y crónicos en la comunidad</ref-titletext> </ref-title> <refd-itemidlist> <itemid idtype="SGR">84979808061</itemid> </refd-itemidlist> <ref-authors> <author seq="1"> <ce:initials>M.</ce:initials> <ce:indexed-name>Alonso M.</ce:indexed-name> <ce:surname>Alonso</ce:surname> </author> <author seq="2"> <ce:initials>M.F.</ce:initials> <ce:indexed-name>Bravo M.F.</ce:indexed-name> <ce:surname>Bravo</ce:surname> </author> <author seq="3"> <ce:initials>A.</ce:initials> <ce:indexed-name>Fernandez-Liria A.</ce:indexed-name> <ce:surname>Fernández-Liria</ce:surname> </author> </ref-authors> <ref-sourcetitle>Revista Asoción Española de Neu-ropsiquiatría</ref-sourcetitle> <ref-publicationyear first="2004"/> <ref-volisspag> <voliss volume="24"/> <pagerange first="25" last="52"/> </ref-volisspag> </ref-info> <ref-fulltext>Alonso, M., Bravo, M. F., y Fernández-Liria, A. (2004). Origen y desarrollo de los programas de seguimiento y cuidados para pacientes mentales graves y crónicos en la comunidad. Revista Asoción Española de Neu-ropsiquiatría, 24, 25-52.</ref-fulltext> </reference> <reference id="2"> <ref-info> <refd-itemidlist> <itemid idtype="SGR">84867465204</itemid> </refd-itemidlist> <ref-sourcetitle>Manual Diag-nóstico y Estadístico de los Trastornos Mentales (4.<sup>a</sup> Ed., Texto Revisado)</ref-sourcetitle> <ref-publicationyear first="2002"/> <ref-text>American Psychiatric Association, Barcelona: Masson. Versión original inglesa, 2000</ref-text> </ref-info> <ref-fulltext>American Psychiatric Association (2002). Manual Diag-nóstico y Estadístico de los Trastornos Mentales (4.<sup>a</sup> ed., texto revisado). Barcelona: Masson. (Versión original inglesa, 2000).</ref-fulltext> </reference> <reference id="3"> <ref-info> <refd-itemidlist> <itemid idtype="SGR">18844371053</itemid> </refd-itemidlist> <ref-authors> <author seq="1"> <ce:initials>L.</ce:initials> <ce:indexed-name>Appleby L.</ce:indexed-name> <ce:surname>Appleby</ce:surname> </author> </ref-authors> <ref-sourcetitle>The National Service Framework for Mental Health - Five Years on</ref-sourcetitle> <ref-publicationyear first="2004"/> <ref-text>Londres: Departament of Health</ref-text> </ref-info> <ref-fulltext>Appleby, L. (2004). The national service framework for mental health - five years on. Londres: Departament of Health.</ref-fulltext> </reference> <reference id="4"> <ref-info> <ref-title> <ref-titletext>An observational, "real life" trial of the introduction of assertive community treatment in a geographically defined area using clinical rather than service use outcome criteria</ref-titletext> </ref-title> <refd-itemidlist> <itemid idtype="SGR">34247521944</itemid> </refd-itemidlist> <ref-authors> <author seq="1"> <ce:initials>M.</ce:initials> <ce:indexed-name>Bak M.</ce:indexed-name> <ce:surname>Bak</ce:surname> </author> <author seq="2"> <ce:initials>J.</ce:initials> <ce:indexed-name>Van Os J.</ce:indexed-name> <ce:surname>Van Os</ce:surname> </author> <author seq="3"> <ce:initials>P.</ce:initials> <ce:indexed-name>Delespaul P.</ce:indexed-name> <ce:surname>Delespaul</ce:surname> </author> <author seq="4"> <ce:initials>A.</ce:initials> <ce:indexed-name>Bie A.</ce:indexed-name> <ce:surname>Bie</ce:surname> </author> <author seq="5"> <ce:initials>J.</ce:initials> <ce:indexed-name>Campo J.</ce:indexed-name> <ce:surname>Campo</ce:surname> </author> <author seq="6"> <ce:initials>G.</ce:initials> <ce:indexed-name>Poddighe G.</ce:indexed-name> <ce:surname>Poddighe</ce:surname> </author> <author seq="7"> <ce:initials>M.</ce:initials> <ce:indexed-name>Drukker M.</ce:indexed-name> <ce:surname>Drukker</ce:surname> </author> </ref-authors> <ref-sourcetitle>Social Psychiatry and Psychiatric Epidemiology</ref-sourcetitle> <ref-publicationyear first="2007"/> <ref-volisspag> <voliss issue="2" volume="42"/> <pagerange first="125" last="130"/> </ref-volisspag> <ref-text>DOI 10.1007/s00127-006-0147-y</ref-text> </ref-info> <ref-fulltext>Bak, M., van Os, J., Delespaul, P., de Bie, A., Ácampo, J., Poddighe, G., y Drukker, M. (2007). An observational, «real life» trial of the introduction of assertive community treatment in a geographically defined area using clinical rather than service use outcome criteria. Social Psychiatry and Psychiatric Epidemiology, 42, 125-30. (Pubitemid 46647113)</ref-fulltext> </reference> <reference id="5"> <ref-info> <ref-title> <ref-titletext>Assertive community treatment for people with severe mental illness: Critical ingredients and impact on patients</ref-titletext> </ref-title> <refd-itemidlist> <itemid idtype="SGR">0035076085</itemid> </refd-itemidlist> <ref-authors> <author seq="1"> <ce:initials>G.R.</ce:initials> <ce:indexed-name>Bond G.R.</ce:indexed-name> <ce:surname>Bond</ce:surname> </author> <author seq="2"> <ce:initials>R.E.</ce:initials> <ce:indexed-name>Drake R.E.</ce:indexed-name> <ce:surname>Drake</ce:surname> </author> <author seq="3"> <ce:initials>K.T.</ce:initials> <ce:indexed-name>Mueser K.T.</ce:indexed-name> <ce:surname>Mueser</ce:surname> </author> <author seq="4"> <ce:initials>E.</ce:initials> <ce:indexed-name>Latimer E.</ce:indexed-name> <ce:surname>Latimer</ce:surname> </author> </ref-authors> <ref-sourcetitle>Disease Management and Health Outcomes</ref-sourcetitle> <ref-publicationyear first="2001"/> <ref-volisspag> <voliss issue="3" volume="9"/> <pagerange first="141" last="159"/> </ref-volisspag> </ref-info> <ref-fulltext>Bond, G. R., Drake, R. E., Mueser, K. T., y Latimer, E. (2001). Assertive community treatment for people with severe mental illness: Critical ingredients and impact on patients. Disease Management and Health Outcomes, 9, 141-159. (Pubitemid 32240880)</ref-fulltext> </reference> <reference id="6"> <ref-info> <ref-title> <ref-titletext>Assertive outreach for frequent users of psychiatric hospitals: A meta-analysis</ref-titletext> </ref-title> <refd-itemidlist> <itemid idtype="SGR">0028893209</itemid> </refd-itemidlist> <ref-authors> <author seq="1"> <ce:initials>G.R.</ce:initials> <ce:indexed-name>Bond G.R.</ce:indexed-name> <ce:surname>Bond</ce:surname> </author> <author seq="2"> <ce:initials>J.H.</ce:initials> <ce:indexed-name>McGrew J.H.</ce:indexed-name> <ce:surname>McGrew</ce:surname> </author> <author seq="3"> <ce:initials>D.M.</ce:initials> <ce:indexed-name>Fekete D.M.</ce:indexed-name> <ce:surname>Fekete</ce:surname> </author> </ref-authors> <ref-sourcetitle>Journal Mental Health Administration</ref-sourcetitle> <ref-publicationyear first="1995"/> <ref-volisspag> <voliss volume="22"/> <pagerange first="4" last="16"/> </ref-volisspag> </ref-info> <ref-fulltext>Bond, G. R., McGrew, J. H., y Fekete, D. M. (1995). Assertive outreach for frequent users of psychiatric hospitals: a meta-analysis. Journal Mental Health Administration, 22, 4-16.</ref-fulltext> </reference> <reference id="7"> <ref-info> <ref-title> <ref-titletext>Use of intensive case management to reduce time in hospital in people with severe mental illness: Systematic review and meta-regression</ref-titletext> </ref-title> <refd-itemidlist> <itemid idtype="SGR">34548175719</itemid> </refd-itemidlist> <ref-authors> <author seq="1"> <ce:initials>T.</ce:initials> <ce:indexed-name>Burns T.</ce:indexed-name> <ce:surname>Burns</ce:surname> </author> <author seq="2"> <ce:initials>J.</ce:initials> <ce:indexed-name>Catty J.</ce:indexed-name> <ce:surname>Catty</ce:surname> </author> <author seq="3"> <ce:initials>M.</ce:initials> <ce:indexed-name>Dash M.</ce:indexed-name> <ce:surname>Dash</ce:surname> </author> <author seq="4"> <ce:initials>C.</ce:initials> <ce:indexed-name>Roberts C.</ce:indexed-name> <ce:surname>Roberts</ce:surname> </author> <author seq="5"> <ce:initials>A.</ce:initials> <ce:indexed-name>Lockwood A.</ce:indexed-name> <ce:surname>Lockwood</ce:surname> </author> <author seq="6"> <ce:initials>M.</ce:initials> <ce:indexed-name>Marshall M.</ce:indexed-name> <ce:surname>Marshall</ce:surname> </author> </ref-authors> <ref-sourcetitle>British Medical Journal</ref-sourcetitle> <ref-publicationyear first="2007"/> <ref-volisspag> <voliss issue="7615" volume="335"/> <pagerange first="336" last="340"/> </ref-volisspag> <ref-text>DOI 10.1136/bmj.39251.599259.55</ref-text> </ref-info> <ref-fulltext>Burns, T., Catty, J., Dash, M., Roberts C., Lockwood, A., y Marshall M. (2007). Use of intensive case management to reduce time in hospital in people with severe mental illness: systematic review and meta-regression. British Medical Journal, 335, 336-340. (Pubitemid 47310867)</ref-fulltext> </reference> <reference id="8"> <ref-info> <ref-title> <ref-titletext>Case management and assertive community treatment in europe</ref-titletext> </ref-title> <refd-itemidlist> <itemid idtype="SGR">0035003341</itemid> </refd-itemidlist> <ref-authors> <author seq="1"> <ce:initials>T.</ce:initials> <ce:indexed-name>Burns T.</ce:indexed-name> <ce:surname>Burns</ce:surname> </author> <author seq="2"> <ce:initials>A.</ce:initials> <ce:indexed-name>Fioritti A.</ce:indexed-name> <ce:surname>Fioritti</ce:surname> </author> <author seq="3"> <ce:initials>F.</ce:initials> <ce:indexed-name>Holloway F.</ce:indexed-name> <ce:surname>Holloway</ce:surname> </author> <author seq="4"> <ce:initials>U.</ce:initials> <ce:indexed-name>Malm U.</ce:indexed-name> <ce:surname>Malm</ce:surname> </author> <author seq="5"> <ce:initials>W.</ce:initials> <ce:indexed-name>Rossler W.</ce:indexed-name> <ce:surname>Rossler</ce:surname> </author> </ref-authors> <ref-sourcetitle>Psychiatric Services</ref-sourcetitle> <ref-publicationyear first="2001"/> <ref-volisspag> <voliss issue="5" volume="52"/> <pagerange first="631" last="636"/> </ref-volisspag> <ref-text>DOI 10.1176/appi.ps.52.5.631</ref-text> </ref-info> <ref-fulltext>Burns, T., Fioretti A., Holloway F., Malm U., y Rössler W. (2001). Case management and assertive community treatment in Europe. Psychiatric Service, 52, 631-36. (Pubitemid 32429292)</ref-fulltext> </reference> <reference id="9"> <ref-info> <refd-itemidlist> <itemid idtype="SGR">84979808082</itemid> </refd-itemidlist> <ref-authors> <author seq="1"> <ce:initials>J.M.</ce:initials> <ce:indexed-name>Canamares J.M.</ce:indexed-name> <ce:surname>Cañamares</ce:surname> </author> <author seq="2"> <ce:initials>M.A.</ce:initials> <ce:indexed-name>Castejon M.A.</ce:indexed-name> <ce:surname>Castejon</ce:surname> </author> <author seq="3"> <ce:initials>A.</ce:initials> <ce:indexed-name>Florit A.</ce:indexed-name> <ce:surname>Florit</ce:surname> </author> <author seq="4"> <ce:initials>J.</ce:initials> <ce:indexed-name>Gonzalez J.</ce:indexed-name> <ce:surname>González</ce:surname> </author> <author seq="5"> <ce:initials>J.A.</ce:initials> <ce:indexed-name>Hernandez J.A.</ce:indexed-name> <ce:surname>Hernández</ce:surname> </author> <author seq="6"> <ce:initials>A.</ce:initials> <ce:indexed-name>Rodriguez A.</ce:indexed-name> <ce:surname>Rodríguez</ce:surname> </author> </ref-authors> <ref-sourcetitle>Esquizofre-nia</ref-sourcetitle> <ref-publicationyear first="2001"/> <ref-text>Madrid Ed. Síntesis</ref-text> </ref-info> <ref-fulltext>Cañamares, J. M., Castejon, M. A., Florit, A., González J., Hernández, J. A., y Rodríguez, A. (2001). Esquizofre-nia. Madrid Ed. Síntesis.</ref-fulltext> </reference> <reference id="10"> <ref-info> <ref-title> <ref-titletext>Psicoterapia cognitiva basada en la persona para la psicosis perturbadora</ref-titletext> </ref-title> <refd-itemidlist> <itemid idtype="SGR">84979818910</itemid> </refd-itemidlist> <ref-authors> <author seq="1"> <ce:initials>P.</ce:initials> <ce:indexed-name>Chadwick P.</ce:indexed-name> <ce:surname>Chadwick</ce:surname> </author> </ref-authors> <ref-sourcetitle>Madrid: Fun-dación Para la Investigación y Tratamiento de la Esqui-zofrenia y Otras Psicosis</ref-sourcetitle> <ref-publicationyear first="2009"/> </ref-info> <ref-fulltext>Chadwick, P. (2009). Psicoterapia cognitiva basada en la persona para la psicosis perturbadora. Madrid: Fun-dación para la Investigación y Tratamiento de la Esqui-zofrenia y otras Psicosis.</ref-fulltext> </reference> <reference id="11"> <ref-info> <refd-itemidlist> <itemid idtype="SGR">0003577917</itemid> </refd-itemidlist> <ref-authors> <author seq="1"> <ce:initials>J.</ce:initials> <ce:indexed-name>Cohen J.</ce:indexed-name> <ce:surname>Cohen</ce:surname> </author> </ref-authors> <ref-sourcetitle>Statistical Power Analysis for the Behavioral Science</ref-sourcetitle> <ref-publicationyear first="1988"/> <ref-text>2nd ed., Hillsdale, NJ: Lawrence Erl-baum Associates</ref-text> </ref-info> <ref-fulltext>Cohen, J. (1988). Statistical power analysis for the behavioral science (2nd ed.). Hillsdale, NJ: Lawrence Erl-baum Associates.</ref-fulltext> </reference> <reference id="12"> <ref-info> <ref-title> <ref-titletext>Tratamiento cognitivo-conductual de las ideas delirantes de un paciente es-quizofrénico</ref-titletext> </ref-title> <refd-itemidlist> <itemid idtype="SGR">84979820826</itemid> </refd-itemidlist> <ref-authors> <author seq="1"> <ce:initials>C.</ce:initials> <ce:indexed-name>Cuevas C.</ce:indexed-name> <ce:surname>Cuevas</ce:surname> </author> <author seq="2"> <ce:initials>S.</ce:initials> <ce:indexed-name>Perona S.</ce:indexed-name> <ce:surname>Perona</ce:surname> </author> </ref-authors> <ref-sourcetitle>Revista de Psicopatología y Psicología Clínicia</ref-sourcetitle> <ref-publicationyear first="1997"/> <ref-volisspag> <voliss volume="2"/> <pagerange first="275" last="291"/> </ref-volisspag> </ref-info> <ref-fulltext>Cuevas, C., y Perona, S. (1997). Tratamiento cognitivo-conductual de las ideas delirantes de un paciente es-quizofrénico. Revista de Psicopatología y Psicología Clínicia, 2, 275-291.</ref-fulltext> </reference> <reference id="13"> <ref-info> <ref-title> <ref-titletext>Dissemination of ACT programs</ref-titletext> </ref-title> <refd-itemidlist> <itemid idtype="SGR">0029008832</itemid> </refd-itemidlist> <ref-authors> <author seq="1"> <ce:initials>E.A.</ce:initials> <ce:indexed-name>Deci E.A.</ce:indexed-name> <ce:surname>Deci</ce:surname> </author> <author seq="2"> <ce:initials>A.B.</ce:initials> <ce:indexed-name>Santos A.B.</ce:indexed-name> <ce:surname>Santos</ce:surname> </author> <author seq="3"> <ce:initials>D.W.</ce:initials> <ce:indexed-name>Hiott D.W.</ce:indexed-name> <ce:surname>Hiott</ce:surname> </author> <author seq="4"> <ce:initials>S.</ce:initials> <ce:indexed-name>Schoenwald S.</ce:indexed-name> <ce:surname>Schoenwald</ce:surname> </author> <author seq="5"> <ce:initials>J.I.</ce:initials> <ce:indexed-name>Dias J.I.</ce:indexed-name> <ce:surname>Dias</ce:surname> </author> </ref-authors> <ref-sourcetitle>Psychiatric Services</ref-sourcetitle> <ref-publicationyear first="1995"/> <ref-volisspag> <voliss volume="46"/> <pagerange first="676" last="678"/> </ref-volisspag> </ref-info> <ref-fulltext>Deci, E. A., Santos, A. B., Hiott, D. W., Schoenwald, S., y Dias, J. I. (1995). Dissemination of ACT programs. Psychiatric Services, 46, 676-678.</ref-fulltext> </reference> <reference id="14"> <ref-info> <refd-itemidlist> <itemid idtype="SGR">0003542702</itemid> </refd-itemidlist> <ref-sourcetitle>The Mental Health Policy Implementation Guide. Community Mental Health Teams</ref-sourcetitle> <ref-publicationyear first="2002"/> <ref-text>Department of Health, London: Department of Health</ref-text> </ref-info> <ref-fulltext>Department of Health (2002). The Mental Health Policy Implementation Guide. Community Mental Health Teams. London: Department of Health.</ref-fulltext> </reference> <reference id="15"> <ref-info> <ref-title> <ref-titletext>Técnica de entrenamiento en atención para el tratamiento de la esquizofrenia</ref-titletext> </ref-title> <refd-itemidlist> <itemid idtype="SGR">84979846067</itemid> </refd-itemidlist> <ref-authors> <author seq="1"> <ce:initials>L.</ce:initials> <ce:indexed-name>Diaz L.</ce:indexed-name> <ce:surname>Díaz</ce:surname> </author> <author seq="2"> <ce:initials>C.</ce:initials> <ce:indexed-name>Cuevas C.</ce:indexed-name> <ce:surname>Cuevas</ce:surname> </author> <author seq="3"> <ce:initials>J.M.</ce:initials> <ce:indexed-name>Izquierdo J.M.</ce:indexed-name> <ce:surname>Izquierdo</ce:surname> </author> </ref-authors> <ref-sourcetitle>Revista de Psicopatología y Psicología Clínica</ref-sourcetitle> <ref-publicationyear first="2011"/> <ref-volisspag> <voliss volume="16"/> <pagerange first="145" last="154"/> </ref-volisspag> </ref-info> <ref-fulltext>Díaz, L., Cuevas, C., y Izquierdo, J. M. (2011). Técnica de entrenamiento en atención para el tratamiento de la esquizofrenia. Revista de Psicopatología y Psicología Clínica, 16, 145-154.</ref-fulltext> </reference> <reference id="16"> <ref-info> <ref-title> <ref-titletext>Programas de seguimiento y cuidados para pacientes graves y cróni-cos; un modelo español de case management</ref-titletext> </ref-title> <refd-itemidlist> <itemid idtype="SGR">84979815065</itemid> </refd-itemidlist> <ref-authors> <author seq="1"> <ce:initials>M.</ce:initials> <ce:indexed-name>Donas M.</ce:indexed-name> <ce:surname>Donas</ce:surname> </author> <author seq="2"> <ce:initials>A.</ce:initials> <ce:indexed-name>Fernandez Liria A.</ce:indexed-name> <ce:surname>Fernández Liria</ce:surname> </author> </ref-authors> <ref-sourcetitle>Rehabilitación Psiquiátrica</ref-sourcetitle> <ref-publicationyear first="1997"/> <ref-text>S. Rebolledo. Ed., Santiago de Compostela: Universidad de Santiago</ref-text> </ref-info> <ref-fulltext>Donas, M., y Fernández Liria, A. (1997). Programas de seguimiento y cuidados para pacientes graves y cróni-cos; un modelo español de case management. En S. Rebolledo. (Ed.), Rehabilitación Psiquiátrica. Santiago de Compostela: Universidad de Santiago.</ref-fulltext> </reference> <reference id="17"> <ref-info> <ref-title> <ref-titletext>A real-life observational study of the effectiveness of FACT in a Dutch mental health region</ref-titletext> </ref-title> <refd-itemidlist> <itemid idtype="SGR">61549127602</itemid> </refd-itemidlist> <ref-authors> <author seq="1"> <ce:initials>M.</ce:initials> <ce:indexed-name>Drukker M.</ce:indexed-name> <ce:surname>Drukker</ce:surname> </author> <author seq="2"> <ce:initials>M.</ce:initials> <ce:indexed-name>Maarschalkerweerd M.</ce:indexed-name> <ce:surname>Maarschalkerweerd</ce:surname> </author> <author seq="3"> <ce:initials>M.</ce:initials> <ce:indexed-name>Bak M.</ce:indexed-name> <ce:surname>Bak</ce:surname> </author> <author seq="4"> <ce:initials>G.</ce:initials> <ce:indexed-name>Driessen G.</ce:indexed-name> <ce:surname>Driessen</ce:surname> </author> <author seq="5"> <ce:initials>J.</ce:initials> <ce:indexed-name>Acampo J.</ce:indexed-name> <ce:surname>Àcampo</ce:surname> </author> <author seq="6"> <ce:initials>A.</ce:initials> <ce:indexed-name>De Bie A.</ce:indexed-name> <ce:surname>De Bie</ce:surname> </author> <et-al/> </ref-authors> <ref-sourcetitle>BMC Psychiatry</ref-sourcetitle> <ref-publicationyear first="2008"/> <ref-volisspag> <voliss volume="4"/> <pagerange first="93"/> </ref-volisspag> </ref-info> <ref-fulltext>Drukker, M., Maarschalkerweerd, M., Bak, M., Driessen, G., Àcampo, J., de Bie, A., et. al. (2008). A real-life observational study of the effectiveness of FACT in a Dutch mental health region. BMC Psychiatry 4, 93.</ref-fulltext> </reference> <reference id="18"> <ref-info> <ref-title> <ref-titletext>Efectividad de las terapias psicológicas: Un análisis de la realidad</ref-titletext> </ref-title> <refd-itemidlist> <itemid idtype="SGR">84979797577</itemid> </refd-itemidlist> <ref-authors> <author seq="1"> <ce:initials>E.</ce:initials> <ce:indexed-name>Echeburua E.</ce:indexed-name> <ce:surname>Echeburúa</ce:surname> </author> <author seq="2"> <ce:initials>P.</ce:initials> <ce:indexed-name>De Corral P.</ce:indexed-name> <ce:surname>De Corral</ce:surname> </author> <author seq="3"> <ce:initials>K.</ce:initials> <ce:indexed-name>Salaberria K.</ce:indexed-name> <ce:surname>Salaberría</ce:surname> </author> </ref-authors> <ref-sourcetitle>Revista de Psicopatología y Psicología Clínica</ref-sourcetitle> <ref-publicationyear first="2010"/> <ref-volisspag> <voliss volume="15"/> <pagerange first="85" last="99"/> </ref-volisspag> </ref-info> <ref-fulltext>Echeburúa, E., de Corral, P., y Salaberría, K. (2010). Efectividad de las terapias psicológicas: Un análisis de la realidad. Revista de Psicopatología y Psicología Clínica, 15, 85-99.</ref-fulltext> </reference> <reference id="19"> <ref-info> <ref-title> <ref-titletext>Los pro-gramas de «Case Management»: Conceptos básicos y aplicabilidad</ref-titletext> </ref-title> <refd-itemidlist> <itemid idtype="SGR">84979826590</itemid> </refd-itemidlist> <ref-authors> <author seq="1"> <ce:initials>A.</ce:initials> <ce:indexed-name>Fernandez Liria A.</ce:indexed-name> <ce:surname>Fernández Liria</ce:surname> </author> <author seq="2"> <ce:initials>M.J.</ce:initials> <ce:indexed-name>Garcia Rojo M.J.</ce:indexed-name> <ce:surname>García Rojo</ce:surname> </author> </ref-authors> <ref-sourcetitle>Revista de la Asociación Española de Neuropsiquiatría</ref-sourcetitle> <ref-publicationyear first="1990"/> <ref-volisspag> <voliss volume="32"/> <pagerange first="5" last="15"/> </ref-volisspag> </ref-info> <ref-fulltext>Fernández Liria, A., García Rojo, M. J. (1990). Los pro-gramas de «Case Management»: Conceptos básicos y aplicabilidad. Revista de la Asociación Española de Neuropsiquiatría, 32, 5-15.</ref-fulltext> </reference> <reference id="20"> <ref-info> <ref-title> <ref-titletext>Assertive community treatment across the Atlantic: Comparison of model fidelity in the UK and USA</ref-titletext> </ref-title> <refd-itemidlist> <itemid idtype="SGR">0037336918</itemid> </refd-itemidlist> <ref-authors> <author seq="1"> <ce:initials>M.</ce:initials> <ce:indexed-name>Fiander M.</ce:indexed-name> <ce:surname>Fiander</ce:surname> </author> <author seq="2"> <ce:initials>T.</ce:initials> <ce:indexed-name>Burns T.</ce:indexed-name> <ce:surname>Burns</ce:surname> </author> <author seq="3"> <ce:initials>G.J.</ce:initials> <ce:indexed-name>McHugo G.J.</ce:indexed-name> <ce:surname>McHugo</ce:surname> </author> <author seq="4"> <ce:initials>R.E.</ce:initials> <ce:indexed-name>Drake R.E.</ce:indexed-name> <ce:surname>Drake</ce:surname> </author> </ref-authors> <ref-sourcetitle>British Journal of Psychiatry</ref-sourcetitle> <ref-publicationyear first="2003"/> <ref-volisspag> <voliss issue="MAR." volume="182"/> <pagerange first="248" last="254"/> </ref-volisspag> <ref-text>DOI 10.1192/bjp.182.3.248</ref-text> </ref-info> <ref-fulltext>Fiander M., Burns T., Mchugo J. G., y Drake R. E. (2003). Assertive community treatment across the atlantic: comparison of model fidelity in the UK And USA. British Journal of Pychiatry, 182, 248-254. (Pubitemid 36286739)</ref-fulltext> </reference> <reference id="21"> <ref-info> <refd-itemidlist> <itemid idtype="SGR">0003918698</itemid> </refd-itemidlist> <ref-authors> <author seq="1"> <ce:initials>M.</ce:initials> <ce:indexed-name>First M.</ce:indexed-name> <ce:surname>First</ce:surname> </author> <author seq="2"> <ce:initials>R.L.</ce:initials> <ce:indexed-name>Spitzer R.L.</ce:indexed-name> <ce:surname>Spitzer</ce:surname> </author> <author seq="3"> <ce:initials>M.</ce:initials> <ce:indexed-name>Gibbon M.</ce:indexed-name> <ce:surname>Gibbon</ce:surname> </author> <author seq="4"> <ce:initials>J.B.W.</ce:initials> <ce:indexed-name>Williams J.B.W.</ce:indexed-name> <ce:surname>Williams</ce:surname> </author> </ref-authors> <ref-sourcetitle>Entrevista Clínica Estructurada Para los Tras-tornos del Eje i del DSM-IV (SCID-I)</ref-sourcetitle> <ref-publicationyear first="1999"/> <ref-text>Barcelona: Masson</ref-text> </ref-info> <ref-fulltext>First, M., Spitzer, R. L., Gibbon, M. y Williams, J. B. W. (1999). Entrevista clínica estructurada para los tras-tornos del Eje I del DSM-IV (SCID-I). Barcelona: Masson.</ref-fulltext> </reference> <reference id="22"> <ref-info> <ref-title> <ref-titletext>The quality of life among persons with severe mental illness enrolled in an assertive community treatment program in Japan: 1-year follow-up and analyses</ref-titletext> </ref-title> <refd-itemidlist> <itemid idtype="SGR">33747590353</itemid> </refd-itemidlist> <ref-authors> <author seq="1"> <ce:initials>K.</ce:initials> <ce:indexed-name>Horiuchi K.</ce:indexed-name> <ce:surname>Horiuchi</ce:surname> </author> <author seq="2"> <ce:initials>M.</ce:initials> <ce:indexed-name>Nisihio M.</ce:indexed-name> <ce:surname>Nisihio</ce:surname> </author> <author seq="3"> <ce:initials>I.</ce:initials> <ce:indexed-name>Oshima I.</ce:indexed-name> <ce:surname>Oshima</ce:surname> </author> <author seq="4"> <ce:initials>J.</ce:initials> <ce:indexed-name>Ito J.</ce:indexed-name> <ce:surname>Ito</ce:surname> </author> <author seq="5"> <ce:initials>H.</ce:initials> <ce:indexed-name>Matsuoka H.</ce:indexed-name> <ce:surname>Matsuoka</ce:surname> </author> <author seq="6"> <ce:initials>K.</ce:initials> <ce:indexed-name>Tsukada K.</ce:indexed-name> <ce:surname>Tsukada</ce:surname> </author> </ref-authors> <ref-sourcetitle>Clinical Practice Epidemolo-gical Mental Health</ref-sourcetitle> <ref-publicationyear first="2006"/> <ref-volisspag> <voliss issue="2" volume="31"/> <pagerange first="18"/> </ref-volisspag> </ref-info> <ref-fulltext>Horiuchi, K., Nisihio, M., Oshima, I., Ito, J., Matsuoka, H., y Tsukada, K. (2006). The quality of life among persons with severe mental illness enrolled in an assertive community treatment program in Japan: 1-year follow-up and analyses. Clinical Practice Epidemolo-gical Mental Health, 31, 2: 18.</ref-fulltext> </reference> <reference id="23"> <ref-info> <ref-title> <ref-titletext>The REACT study: A randomised evaluation of assertive community treatment in North London</ref-titletext> </ref-title> <refd-itemidlist> <itemid idtype="SGR">33645830684</itemid> </refd-itemidlist> <ref-authors> <author seq="1"> <ce:initials>H.</ce:initials> <ce:indexed-name>Killaspy H.</ce:indexed-name> <ce:surname>Killaspy</ce:surname> </author> <author seq="2"> <ce:initials>P.</ce:initials> <ce:indexed-name>Bebbington P.</ce:indexed-name> <ce:surname>Bebbington</ce:surname> </author> <author seq="3"> <ce:initials>R.</ce:initials> <ce:indexed-name>Blizard R.</ce:indexed-name> <ce:surname>Blizard</ce:surname> </author> <et-al/> </ref-authors> <ref-sourcetitle>British Medical Journal</ref-sourcetitle> <ref-publicationyear first="2006"/> <ref-volisspag> <voliss volume="332"/> <pagerange first="815" last="820"/> </ref-volisspag> </ref-info> <ref-fulltext>Killaspy, H., Bebbington, P., Blizard, R., et al. (2006). The REACT study: A randomised evaluation of assertive community treatment in North London. British Medical Journal, 332, 815-820.</ref-fulltext> </reference> <reference id="24"> <ref-info> <ref-title> <ref-titletext>El papel del psicólogo clínico en los equipos se seguimiento comunitario al trastorno mental grave</ref-titletext> </ref-title> <refd-itemidlist> <itemid idtype="SGR">84979815069</itemid> </refd-itemidlist> <ref-authors> <author seq="1"> <ce:initials>J.</ce:initials> <ce:indexed-name>Lopez-Santiago J.</ce:indexed-name> <ce:surname>López-Santiago</ce:surname> </author> </ref-authors> <ref-sourcetitle>V Word Congress of Behavioral and Cognitive Therapies</ref-sourcetitle> <ref-publicationyear first="2007"/> <ref-text>Poster presentado al, Barcelona, 12-14 de Julio</ref-text> </ref-info> <ref-fulltext>López-Santiago J. (2007). El papel del psicólogo clínico en los equipos se seguimiento comunitario al trastorno mental grave. Poster presentado al V Word Congress of Behavioral and Cognitive Therapies. Barcelona, 12-14 de Julio.</ref-fulltext> </reference> <reference id="25"> <ref-info> <ref-title> <ref-titletext>Tratamiento asertivo comuni-tario</ref-titletext> </ref-title> <refd-itemidlist> <itemid idtype="SGR">84979845507</itemid> </refd-itemidlist> <ref-authors> <author seq="1"> <ce:initials>J.</ce:initials> <ce:indexed-name>Lopez-Santiago J.</ce:indexed-name> <ce:surname>López-Santiago</ce:surname> </author> </ref-authors> <ref-sourcetitle>Perspectivas Actuales en el Tratamiento de los Trastornos Mentales Graves</ref-sourcetitle> <ref-publicationyear first="2010"/> <ref-text>A., Cangas, e V., Ibáñez Eds., Granada: Editorial Alborán</ref-text> </ref-info> <ref-fulltext>López-Santiago J. (2010). Tratamiento asertivo comuni-tario. En A., Cangas, e V., Ibáñez (Eds.), Perspectivas actuales en el tratamiento de los trastornos mentales graves. Granada: Editorial Alborán.</ref-fulltext> </reference> <reference id="26"> <ref-info> <ref-title> <ref-titletext>PriSM Psychosis Study. Design limitations, questionable conclusions</ref-titletext> </ref-title> <refd-itemidlist> <itemid idtype="SGR">0032756389</itemid> </refd-itemidlist> <ref-authors> <author seq="1"> <ce:initials>M.</ce:initials> <ce:indexed-name>Marshall M.</ce:indexed-name> <ce:surname>Marshall</ce:surname> </author> <author seq="2"> <ce:initials>G.</ce:initials> <ce:indexed-name>Bond G.</ce:indexed-name> <ce:surname>Bond</ce:surname> </author> <author seq="3"> <ce:initials>L.I.</ce:initials> <ce:indexed-name>Stein L.I.</ce:indexed-name> <ce:surname>Stein</ce:surname> </author> <author seq="4"> <ce:initials>G.</ce:initials> <ce:indexed-name>Shepherd G.</ce:indexed-name> <ce:surname>Shepherd</ce:surname> </author> <author seq="5"> <ce:initials>J.</ce:initials> <ce:indexed-name>Mc-Grew J.</ce:indexed-name> <ce:surname>Mc-Grew</ce:surname> </author> <author seq="6"> <ce:initials>J.</ce:initials> <ce:indexed-name>Hoult J.</ce:indexed-name> <ce:surname>Hoult</ce:surname> </author> <et-al/> </ref-authors> <ref-sourcetitle>British Journal of Psychiatry</ref-sourcetitle> <ref-publicationyear first="1999"/> <ref-volisspag> <voliss volume="175"/> <pagerange first="501" last="503"/> </ref-volisspag> </ref-info> <ref-fulltext>Marshall, M., Bond, G., Stein, L. I., Shepherd, G., Mc-Grew, J., Hoult, J., et al. (1999). PriSM Psychosis Study. Design limitations, questionable conclusions. British Journal of Psychiatry, 175, 501-503.</ref-fulltext> </reference> <reference id="27"> <ref-info> <ref-title> <ref-titletext>Case management for people with severe mental disorders (Cochrane review)</ref-titletext> </ref-title> <refd-itemidlist> <itemid idtype="SGR">33846989646</itemid> </refd-itemidlist> <ref-authors> <author seq="1"> <ce:initials>M.</ce:initials> <ce:indexed-name>Marshall M.</ce:indexed-name> <ce:surname>Marshall</ce:surname> </author> <author seq="2"> <ce:initials>A.</ce:initials> <ce:indexed-name>Gray A.</ce:indexed-name> <ce:surname>Gray</ce:surname> </author> <author seq="3"> <ce:initials>A.</ce:initials> <ce:indexed-name>Lockwood A.</ce:indexed-name> <ce:surname>Lockwood</ce:surname> </author> <author seq="4"> <ce:initials>R.</ce:initials> <ce:indexed-name>Green R.</ce:indexed-name> <ce:surname>Green</ce:surname> </author> </ref-authors> <ref-sourcetitle>Cochrane Library</ref-sourcetitle> <ref-publicationyear first="2002"/> <ref-volisspag> <voliss issue="3"/> </ref-volisspag> <ref-text>Oxford: Update Software</ref-text> </ref-info> <ref-fulltext>Marshall, M., Gray, A., Lockwood, A. y Green, R. (2002). Case management for people with severe mental disorders (Cochrane review). Cochrane Library (Issue 3). Oxford: Update Software.</ref-fulltext> </reference> <reference id="28"> <ref-info> <ref-title> <ref-titletext>Assertive community treatment for people with severe mental disorders (Cochrane review)</ref-titletext> </ref-title> <refd-itemidlist> <itemid idtype="SGR">0010550493</itemid> </refd-itemidlist> <ref-authors> <author seq="1"> <ce:initials>M.</ce:initials> <ce:indexed-name>Marshall M.</ce:indexed-name> <ce:surname>Marshall</ce:surname> </author> <author seq="2"> <ce:initials>A.</ce:initials> <ce:indexed-name>Lockwood A.</ce:indexed-name> <ce:surname>Lockwood</ce:surname> </author> </ref-authors> <ref-sourcetitle>Cochrane Library</ref-sourcetitle> <ref-publicationyear first="2002"/> <ref-volisspag> <voliss issue="3"/> </ref-volisspag> <ref-text>Oxford: Update Software</ref-text> </ref-info> <ref-fulltext>Marshall, M., y Lockwood, A. (2002) Assertive community treatment for people with severe mental disorders (Cochrane review). Cochrane Library (Issue 3). Oxford: Update Software.</ref-fulltext> </reference> <reference id="29"> <ref-info> <ref-title> <ref-titletext>El modelo Avilés para la implantación del tratamiento asertivo comunitario: Un pacto con la realidad</ref-titletext> </ref-title> <refd-itemidlist> <itemid idtype="SGR">84979821304</itemid> </refd-itemidlist> <ref-authors> <author seq="1"> <ce:initials>J.J.</ce:initials> <ce:indexed-name>Martinez Jambrina J.J.</ce:indexed-name> <ce:surname>Martínez Jambrina</ce:surname> </author> </ref-authors> <ref-sourcetitle>Cuadernos de Psiquiatria Co-munitaria</ref-sourcetitle> <ref-publicationyear first="2008"/> <ref-volisspag> <voliss volume="7"/> <pagerange first="147" last="159"/> </ref-volisspag> </ref-info> <ref-fulltext>Martínez Jambrina, J. J. (2008). El modelo Avilés para la implantación del tratamiento asertivo comunitario: Un pacto con la realidad. Cuadernos de Psiquiatria Co-munitaria, 7, 147-159.</ref-fulltext> </reference> <reference id="30"> <ref-info> <ref-title> <ref-titletext>Extrahos-pital management of severe mental illness: Feasibility and effects of social functioning</ref-titletext> </ref-title> <refd-itemidlist> <itemid idtype="SGR">0015677132</itemid> </refd-itemidlist> <ref-authors> <author seq="1"> <ce:initials>A.J.</ce:initials> <ce:indexed-name>Marx A.J.</ce:indexed-name> <ce:surname>Marx</ce:surname> </author> <author seq="2"> <ce:initials>M.A.</ce:initials> <ce:indexed-name>Test M.A.</ce:indexed-name> <ce:surname>Test</ce:surname> </author> <author seq="3"> <ce:initials>L.L.</ce:initials> <ce:indexed-name>Stein L.L.</ce:indexed-name> <ce:surname>Stein</ce:surname> </author> </ref-authors> <ref-sourcetitle>Archives of General Psychiatry</ref-sourcetitle> <ref-publicationyear first="1973"/> <ref-volisspag> <voliss volume="29"/> <pagerange first="505" last="511"/> </ref-volisspag> </ref-info> <ref-fulltext>Marx, A. J., Test, M. A., y Stein, L. L. (1973). Extrahos-pital management of severe mental illness: feasibility and effects of social functioning. Archives of General Psychiatry, 29, 505-511.</ref-fulltext> </reference> <reference id="31"> <ref-info> <ref-title> <ref-titletext>Critical ingredients of assertive community treatment: Judgments of the experts</ref-titletext> </ref-title> <refd-itemidlist> <itemid idtype="SGR">0029026417</itemid> </refd-itemidlist> <ref-authors> <author seq="1"> <ce:initials>J.</ce:initials> <ce:indexed-name>McGrew J.</ce:indexed-name> <ce:surname>McGrew</ce:surname> </author> <author seq="2"> <ce:initials>G.R.</ce:initials> <ce:indexed-name>Bond G.R.</ce:indexed-name> <ce:surname>Bond</ce:surname> </author> </ref-authors> <ref-sourcetitle>Journal of Mental Health Administration</ref-sourcetitle> <ref-publicationyear first="1995"/> <ref-volisspag> <voliss volume="22"/> <pagerange first="113" last="125"/> </ref-volisspag> </ref-info> <ref-fulltext>McGrew, J., y Bond, G. R. (1995). Critical ingredients of assertive community treatment: Judgments of the experts. Journal of Mental Health Administration, 22, 113-125.</ref-fulltext> </reference> <reference id="32"> <ref-info> <refd-itemidlist> <itemid idtype="SGR">77955106350</itemid> </refd-itemidlist> <ref-sourcetitle>Estra-tegia de Salud Mental del Sistema Nacional de Salud</ref-sourcetitle> <ref-publicationyear first="2007"/> <ref-text>Ministerio de Sanidad y Consumo MSC, Madrid: MSyC</ref-text> </ref-info> <ref-fulltext>Ministerio de Sanidad y Consumo (MSC) (2007). Estra-tegia de salud mental del Sistema Nacional de Salud. Madrid: MSyC.</ref-fulltext> </reference> <reference id="33"> <ref-info> <ref-title> <ref-titletext>La psicología basada en la evidencia y el diseño y evaluación de tratamientos psicológicos eficaces</ref-titletext> </ref-title> <refd-itemidlist> <itemid idtype="SGR">84979725929</itemid> </refd-itemidlist> <ref-authors> <author seq="1"> <ce:initials>J.A.</ce:initials> <ce:indexed-name>Moraira J.A.</ce:indexed-name> <ce:surname>Moraira</ce:surname> </author> <author seq="2"> <ce:initials>V.A.</ce:initials> <ce:indexed-name>Martinez V.A.</ce:indexed-name> <ce:surname>Martínez</ce:surname> </author> </ref-authors> <ref-sourcetitle>Revista de Psico-patología y Psicología Clínica</ref-sourcetitle> <ref-publicationyear first="2011"/> <ref-volisspag> <voliss volume="16"/> <pagerange first="81" last="100"/> </ref-volisspag> </ref-info> <ref-fulltext>Moraira, J. A., y Martínez, V. A. (2011). La psicología basada en la evidencia y el diseño y evaluación de tratamientos psicológicos eficaces. Revista de Psico-patología y Psicología Clínica, 16, 81-100.</ref-fulltext> </reference> <reference id="34"> <ref-info> <ref-title> <ref-titletext>Models of community care for severe mental illness: A review of research on case management</ref-titletext> </ref-title> <refd-itemidlist> <itemid idtype="SGR">0031883645</itemid> </refd-itemidlist> <ref-authors> <author seq="1"> <ce:initials>K.T.</ce:initials> <ce:indexed-name>Mueser K.T.</ce:indexed-name> <ce:surname>Mueser</ce:surname> </author> <author seq="2"> <ce:initials>G.R.</ce:initials> <ce:indexed-name>Bond G.R.</ce:indexed-name> <ce:surname>Bond</ce:surname> </author> <author seq="3"> <ce:initials>R.E.</ce:initials> <ce:indexed-name>Drake R.E.</ce:indexed-name> <ce:surname>Drake</ce:surname> </author> <author seq="4"> <ce:initials>S.G.</ce:initials> <ce:indexed-name>Resnick S.G.</ce:indexed-name> <ce:surname>Resnick</ce:surname> </author> </ref-authors> <ref-sourcetitle>Schizophrenia Bulletin</ref-sourcetitle> <ref-publicationyear first="1998"/> <ref-volisspag> <voliss issue="1" volume="24"/> <pagerange first="37" last="74"/> </ref-volisspag> </ref-info> <ref-fulltext>Mueser, K. T., Bond, G. R., Drake, R. E., y Resnick, S. G. (1998). Models of community care for severe mental illness: A review of research on case management. Schizophrenia Bulletin, 4, 37-74. (Pubitemid 28128489)</ref-fulltext> </reference> <reference id="35"> <ref-info> <ref-title> <ref-titletext>Clinical guideline 82</ref-titletext> </ref-title> <refd-itemidlist> <itemid idtype="SGR">84979839914</itemid> </refd-itemidlist> <ref-sourcetitle>Schizophrenia: Core Interventions in the Treatment and Management of Schizophrenia in Primary and Secondary Care</ref-sourcetitle> <ref-publicationyear first="2009"/> <ref-text>NICE, London: National Institute for Health and Clinical Excellence</ref-text> </ref-info> <ref-fulltext>NICE (2009). Clinical Guideline 82. Schizophrenia: Core interventions in the treatment and management of schizophrenia in primary and secondary care. London: National Institute for Health and Clinical Excellence.</ref-fulltext> </reference> <reference id="36"> <ref-info> <ref-title> <ref-titletext>Tratamiento de rehabili-tación neurocognitiva de la esquizofrenia</ref-titletext> </ref-title> <refd-itemidlist> <itemid idtype="SGR">84979845495</itemid> </refd-itemidlist> <ref-authors> <author seq="1"> <ce:initials>R.</ce:initials> <ce:indexed-name>Penades R.</ce:indexed-name> <ce:surname>Penadés</ce:surname> </author> <author seq="2"> <ce:initials>C.</ce:initials> <ce:indexed-name>Gasto C.</ce:indexed-name> <ce:surname>Gastó</ce:surname> </author> </ref-authors> <ref-sourcetitle>Barcelona: Herder</ref-sourcetitle> <ref-publicationyear first="2010"/> </ref-info> <ref-fulltext>Penadés, R., y Gastó, C. (2010). Tratamiento de rehabili-tación neurocognitiva de la esquizofrenia. Barcelona: Herder</ref-fulltext> </reference> <reference id="37"> <ref-info> <refd-itemidlist> <itemid idtype="SGR">30544451138</itemid> </refd-itemidlist> <ref-authors> <author seq="1"> <ce:initials>M.</ce:initials> <ce:indexed-name>Perez M.</ce:indexed-name> <ce:surname>Pérez</ce:surname> </author> <author seq="2"> <ce:initials>J.R.</ce:initials> <ce:indexed-name>Fernandez J.R.</ce:indexed-name> <ce:surname>Fernández</ce:surname> </author> <author seq="3"> <ce:initials>C.</ce:initials> <ce:indexed-name>Fernandez C.</ce:indexed-name> <ce:surname>Fernández</ce:surname> </author> <author seq="4"> <ce:initials>I.</ce:initials> <ce:indexed-name>Amigo I.</ce:indexed-name> <ce:surname>Amigo</ce:surname> </author> </ref-authors> <ref-sourcetitle>Guía de Tratamientos Psicológicos Eficaces I: Adultos</ref-sourcetitle> <ref-publicationyear first="2003"/> <ref-text>Madrid: Pirámide</ref-text> </ref-info> <ref-fulltext>Pérez, M., Fernández, J. R., Fernández, C., y Amigo, I. (2003). Guía de tratamientos psicológicos eficaces I: Adultos. Madrid: Pirámide.</ref-fulltext> </reference> <reference id="38"> <ref-info> <ref-title> <ref-titletext>Moving assertive community treatment into standard practice</ref-titletext> </ref-title> <refd-itemidlist> <itemid idtype="SGR">0034976774</itemid> </refd-itemidlist> <ref-authors> <author seq="1"> <ce:initials>S.D.</ce:initials> <ce:indexed-name>Phillips S.D.</ce:indexed-name> <ce:surname>Phillips</ce:surname> </author> <author seq="2"> <ce:initials>B.J.</ce:initials> <ce:indexed-name>Burns B.J.</ce:indexed-name> <ce:surname>Burns</ce:surname> </author> <author seq="3"> <ce:initials>E.R.</ce:initials> <ce:indexed-name>Edgar E.R.</ce:indexed-name> <ce:surname>Edgar</ce:surname> </author> <author seq="4"> <ce:initials>K.T.</ce:initials> <ce:indexed-name>Mueser K.T.</ce:indexed-name> <ce:surname>Mueser</ce:surname> </author> <author seq="5"> <ce:initials>K.W.</ce:initials> <ce:indexed-name>Linkins K.W.</ce:indexed-name> <ce:surname>Linkins</ce:surname> </author> <author seq="6"> <ce:initials>R.A.</ce:initials> <ce:indexed-name>Rosenheck R.A.</ce:indexed-name> <ce:surname>Rosenheck</ce:surname> </author> <author seq="7"> <ce:initials>R.E.</ce:initials> <ce:indexed-name>Drake R.E.</ce:indexed-name> <ce:surname>Drake</ce:surname> </author> <author seq="8"> <ce:initials>E.C.</ce:initials> <ce:indexed-name>McDonel Herr E.C.</ce:indexed-name> <ce:surname>McDonel Herr</ce:surname> </author> </ref-authors> <ref-sourcetitle>Psychiatric Services</ref-sourcetitle> <ref-publicationyear first="2001"/> <ref-volisspag> <voliss issue="6" volume="52"/> <pagerange first="771" last="779"/> </ref-volisspag> <ref-text>DOI 10.1176/appi.ps.52.6.771</ref-text> </ref-info> <ref-fulltext>Phillips, S. D., Burns, B., Edgar, E. R., Mueser, K. T., Linkins, K. W., Rosenheck, R. A., Drake, R. E., y McDonel-Herr, E. C. (2001). Moving Assertive Community Treatment In to Standard Practice. Psychiatry Services, 52, 771-779. (Pubitemid 32577435)</ref-fulltext> </reference> <reference id="39"> <ref-info> <ref-title> <ref-titletext>Marco General y Conceptualización</ref-titletext> </ref-title> <refd-itemidlist> <itemid idtype="SGR">84979845547</itemid> </refd-itemidlist> <ref-authors> <author seq="1"> <ce:initials>A.</ce:initials> <ce:indexed-name>Rodriguez A.</ce:indexed-name> <ce:surname>Rodríguez</ce:surname> </author> <author seq="2"> <ce:initials>M.F.</ce:initials> <ce:indexed-name>Bravo M.F.</ce:indexed-name> <ce:surname>Bravo</ce:surname> </author> </ref-authors> <ref-sourcetitle>Rehabilitación Psicosocial y Tratamiento Integral del Trastorno Mental Severo</ref-sourcetitle> <ref-publicationyear first="2003"/> <ref-text>C. Gisbert Ed., Madrid: AEN</ref-text> </ref-info> <ref-fulltext>Rodríguez, A., y Bravo, M. F. (2003). Marco General y Conceptualización. En C. Gisbert (Ed.), Rehabilitación Psicosocial y Tratamiento Integral del Trastorno mental Severo. Madrid: AEN.</ref-fulltext> </reference> <reference id="40"> <ref-info> <ref-title> <ref-titletext>Does case management work? The evidence and the abuse of evidence-based medicine</ref-titletext> </ref-title> <refd-itemidlist> <itemid idtype="SGR">0035674044</itemid> </refd-itemidlist> <ref-authors> <author seq="1"> <ce:initials>A.</ce:initials> <ce:indexed-name>Rosen A.</ce:indexed-name> <ce:surname>Rosen</ce:surname> </author> <author seq="2"> <ce:initials>M.</ce:initials> <ce:indexed-name>Teesson M.</ce:indexed-name> <ce:surname>Teesson</ce:surname> </author> </ref-authors> <ref-sourcetitle>Australian and New Zealand Journal of Psychiatry</ref-sourcetitle> <ref-publicationyear first="2001"/> <ref-volisspag> <voliss issue="6" volume="35"/> <pagerange first="731" last="746"/> </ref-volisspag> <ref-text>DOI 10.1046/j.1440-1614.2001.00956.x</ref-text> </ref-info> <ref-fulltext>Rosen, A. y Teesson, M. (2001). Does case management work? The evidence and the abuse of evidence based medicine. Australian and New Zealand Journal of Psychiatry, 35, 731-746. (Pubitemid 34048444)</ref-fulltext> </reference> <reference id="41"> <ref-info> <ref-title> <ref-titletext>Assertive Community Treatment-Issues from scientific and clinical literature with implications for practice</ref-titletext> </ref-title> <refd-itemidlist> <itemid idtype="SGR">44449134587</itemid> </refd-itemidlist> <ref-authors> <author seq="1"> <ce:initials>A.</ce:initials> <ce:indexed-name>Rosen A.</ce:indexed-name> <ce:surname>Rosen</ce:surname> </author> <author seq="2"> <ce:initials>K.T.</ce:initials> <ce:indexed-name>Mueser K.T.</ce:indexed-name> <ce:surname>Mueser</ce:surname> </author> <author seq="3"> <ce:initials>M.</ce:initials> <ce:indexed-name>Teesson M.</ce:indexed-name> <ce:surname>Teesson</ce:surname> </author> </ref-authors> <ref-sourcetitle>Journal of Rehabilitation Reseach and Development</ref-sourcetitle> <ref-publicationyear first="2007"/> <ref-volisspag> <voliss volume="44"/> <pagerange first="813" last="826"/> </ref-volisspag> </ref-info> <ref-fulltext>Rosen, A., Mueser, K. T., y Teesson, M. (2007). Assertive Community Treatment-Issues from scientific and clinical literature with implications for practice. Journal of Rehabilitation Reseach and Development, 44, 813-826.</ref-fulltext> </reference> <reference id="42"> <ref-info> <ref-title> <ref-titletext>Aproximaciones psicológicas al tratamiento de las esquizofrenias</ref-titletext> </ref-title> <refd-itemidlist> <itemid idtype="SGR">84979807323</itemid> </refd-itemidlist> <ref-authors> <author seq="1"> <ce:initials>E.</ce:initials> <ce:indexed-name>Santiago E.</ce:indexed-name> <ce:surname>Santiago</ce:surname> </author> <author seq="2"> <ce:initials>A.</ce:initials> <ce:indexed-name>Martinez De Salazar A.</ce:indexed-name> <ce:surname>Martínez De Salazar</ce:surname> </author> <author seq="3"> <ce:initials>J.C.</ce:initials> <ce:indexed-name>Ibanez J.C.</ce:indexed-name> <ce:surname>Ibáñez</ce:surname> </author> <author seq="4"> <ce:initials>M.J.</ce:initials> <ce:indexed-name>Sanchez M.J.</ce:indexed-name> <ce:surname>Sánchez</ce:surname> </author> </ref-authors> <ref-sourcetitle>Revista de Psico-patología y Psicología Clínica</ref-sourcetitle> <ref-publicationyear first="1999"/> <ref-volisspag> <voliss volume="4"/> <pagerange first="181" last="201"/> </ref-volisspag> </ref-info> <ref-fulltext>Santiago, E., Martínez de Salazar, A., Ibáñez, J. C., y Sánchez, M. J. (1999). Aproximaciones psicológicas al tratamiento de las esquizofrenias. Revista de Psico-patología y Psicología Clínica, 4, 181-201.</ref-fulltext> </reference> <reference id="43"> <ref-info> <ref-title> <ref-titletext>Alternative to the hospital: A controlled study</ref-titletext> </ref-title> <refd-itemidlist> <itemid idtype="SGR">0016706717</itemid> </refd-itemidlist> <ref-authors> <author seq="1"> <ce:initials>L.I.</ce:initials> <ce:indexed-name>Stein L.I.</ce:indexed-name> <ce:surname>Stein</ce:surname> </author> <author seq="2"> <ce:initials>M.A.</ce:initials> <ce:indexed-name>Test M.A.</ce:indexed-name> <ce:surname>Test</ce:surname> </author> <author seq="3"> <ce:initials>A.J.</ce:initials> <ce:indexed-name>Marx A.J.</ce:indexed-name> <ce:surname>Marx</ce:surname> </author> </ref-authors> <ref-sourcetitle>American Journal of Psychiatry</ref-sourcetitle> <ref-publicationyear first="1975"/> <ref-volisspag> <voliss volume="132"/> <pagerange first="517" last="522"/> </ref-volisspag> </ref-info> <ref-fulltext>Stein, L. I., Test, M. A., y Marx, A. J. (1975). Alternative to the hospital: A controlled study. American Journal of Psychiatry, 132, 517-522.</ref-fulltext> </reference> <reference id="44"> <ref-info> <refd-itemidlist> <itemid idtype="SGR">0004029172</itemid> </refd-itemidlist> <ref-authors> <author seq="1"> <ce:initials>L.I.</ce:initials> <ce:indexed-name>Stein L.I.</ce:indexed-name> <ce:surname>Stein</ce:surname> </author> <author seq="2"> <ce:initials>A.B.</ce:initials> <ce:indexed-name>Santos A.B.</ce:indexed-name> <ce:surname>Santos</ce:surname> </author> </ref-authors> <ref-sourcetitle>Assertive Community Treatment of Persons with Severe Mental Illness</ref-sourcetitle> <ref-publicationyear first="1998"/> <ref-text>New York: Norton</ref-text> </ref-info> <ref-fulltext>Stein, L. I., y Santos, A. B. (1998). Assertive community treatment of persons with severe mental illness. New York: Norton.</ref-fulltext> </reference> <reference id="45"> <ref-info> <ref-title> <ref-titletext>Alternative to mental hospital treatment. I. Conceptual model, treatment program, and clinical evaluation</ref-titletext> </ref-title> <refd-itemidlist> <itemid idtype="SGR">0018901611</itemid> </refd-itemidlist> <ref-authors> <author seq="1"> <ce:initials>L.I.</ce:initials> <ce:indexed-name>Stein L.I.</ce:indexed-name> <ce:surname>Stein</ce:surname> </author> <author seq="2"> <ce:initials>M.A.</ce:initials> <ce:indexed-name>Test M.A.</ce:indexed-name> <ce:surname>Test</ce:surname> </author> </ref-authors> <ref-sourcetitle>Archives of General Psychiatry</ref-sourcetitle> <ref-publicationyear first="1980"/> <ref-volisspag> <voliss issue="4" volume="37"/> <pagerange first="392" last="397"/> </ref-volisspag> </ref-info> <ref-fulltext>Stein, L. I., y Test, M. A. (1980). Alternative to mental hospital treatment: I. Conceptual model, treatment program, and clinical evaluation. Archives of General Psychiatry, 37, 392-397. (Pubitemid 10100566)</ref-fulltext> </reference> <reference id="46"> <ref-info> <ref-title> <ref-titletext>Program fidelity in assertive community treatment: Development and use of a measure</ref-titletext> </ref-title> <refd-itemidlist> <itemid idtype="SGR">0031925344</itemid> </refd-itemidlist> <ref-authors> <author seq="1"> <ce:initials>G.B.</ce:initials> <ce:indexed-name>Teague G.B.</ce:indexed-name> <ce:surname>Teague</ce:surname> </author> <author seq="2"> <ce:initials>G.R.</ce:initials> <ce:indexed-name>Bond G.R.</ce:indexed-name> <ce:surname>Bond</ce:surname> </author> <author seq="3"> <ce:initials>R.E.</ce:initials> <ce:indexed-name>Drake R.E.</ce:indexed-name> <ce:surname>Drake</ce:surname> </author> </ref-authors> <ref-sourcetitle>American Journal of Orthopsychiatry</ref-sourcetitle> <ref-publicationyear first="1998"/> <ref-volisspag> <voliss issue="2" volume="68"/> <pagerange first="216" last="232"/> </ref-volisspag> <ref-text>DOI 10.1037/h0080331</ref-text> </ref-info> <ref-fulltext>Teague, G. B., Bond, G. R., y Drake, R. E. (1998). Program fidelity in assertive community treatment: Development and use of a measure. American Journal of Or-thopsychiatry, 68, 216-232. (Pubitemid 28215538)</ref-fulltext> </reference> <reference id="47"> <ref-info> <ref-title> <ref-titletext>Alternative to mental hospital treatment. III. Social cost</ref-titletext> </ref-title> <refd-itemidlist> <itemid idtype="SGR">0018820563</itemid> </refd-itemidlist> <ref-authors> <author seq="1"> <ce:initials>M.A.</ce:initials> <ce:indexed-name>Test M.A.</ce:indexed-name> <ce:surname>Test</ce:surname> </author> <author seq="2"> <ce:initials>L.I.</ce:initials> <ce:indexed-name>Stein L.I.</ce:indexed-name> <ce:surname>Stein</ce:surname> </author> </ref-authors> <ref-sourcetitle>Archives of General Psychiatry</ref-sourcetitle> <ref-publicationyear first="1980"/> <ref-volisspag> <voliss issue="4" volume="37"/> <pagerange first="409" last="412"/> </ref-volisspag> </ref-info> <ref-fulltext>Test, M. A., y Stein, L. I. (1980) Alternative to mental hospital treatment: III. Social cost. Archives of General Psychiatry, 37, 409-412. (Pubitemid 10100568)</ref-fulltext> </reference> <reference id="48"> <ref-info> <ref-title> <ref-titletext>From efficacy to effectiveness in community mental health services. PRiSM psychosis study 10</ref-titletext> </ref-title> <refd-itemidlist> <itemid idtype="SGR">0031733101</itemid> </refd-itemidlist> <ref-authors> <author seq="1"> <ce:initials>G.</ce:initials> <ce:indexed-name>Thornicroft G.</ce:indexed-name> <ce:surname>Thornicroft</ce:surname> </author> <author seq="2"> <ce:initials>T.</ce:initials> <ce:indexed-name>Wykes T.</ce:indexed-name> <ce:surname>Wykes</ce:surname> </author> <author seq="3"> <ce:initials>F.</ce:initials> <ce:indexed-name>Holloway F.</ce:indexed-name> <ce:surname>Holloway</ce:surname> </author> <author seq="4"> <ce:initials>S.</ce:initials> <ce:indexed-name>Johnson S.</ce:indexed-name> <ce:surname>Johnson</ce:surname> </author> <author seq="5"> <ce:initials>G.</ce:initials> <ce:indexed-name>Szmukler G.</ce:indexed-name> <ce:surname>Szmukler</ce:surname> </author> </ref-authors> <ref-sourcetitle>British Journal of Psychiatry</ref-sourcetitle> <ref-publicationyear first="1998"/> <ref-volisspag> <voliss issue="NOV." volume="173"/> <pagerange first="423" last="427"/> </ref-volisspag> </ref-info> <ref-fulltext>Thornicroft, G., Wykes, T., Holloway, F., Jonhson, S, Smukler, G. (1998). From efficacy to effectiveness in community mental health services. PRiSM psychosis study, 10. British Journal of Psychiatry, 173, 423-427. (Pubitemid 28506152)</ref-fulltext> </reference> <reference id="49"> <ref-info> <ref-title> <ref-titletext>Components of a modern mental health service: A pragmatic balance of community and hospital care. Overview of systematic evidence</ref-titletext> </ref-title> <refd-itemidlist> <itemid idtype="SGR">4944225889</itemid> </refd-itemidlist> <ref-authors> <author seq="1"> <ce:initials>G.</ce:initials> <ce:indexed-name>Thornicroft G.</ce:indexed-name> <ce:surname>Thornicroft</ce:surname> </author> <author seq="2"> <ce:initials>M.</ce:initials> <ce:indexed-name>Tansella M.</ce:indexed-name> <ce:surname>Tansella</ce:surname> </author> </ref-authors> <ref-sourcetitle>British Journal of Psychiatry</ref-sourcetitle> <ref-publicationyear first="2004"/> <ref-volisspag> <voliss issue="OCT." volume="185"/> <pagerange first="283" last="290"/> </ref-volisspag> <ref-text>DOI 10.1192/bjp.185.4.283</ref-text> </ref-info> <ref-fulltext>Thornicroft, G., y Tansella, M. (2004). Components of a modern mental health service: A pragmatic balance of community and hospital care overview of systematic evidence. British Journal of Psychiatry, 185, 283-290. (Pubitemid 39331329)</ref-fulltext> </reference> <reference id="50"> <ref-info> <refd-itemidlist> <itemid idtype="SGR">84979826837</itemid> </refd-itemidlist> <ref-authors> <author seq="1"> <ce:initials>R.</ce:initials> <ce:indexed-name>Tourino R.</ce:indexed-name> <ce:surname>Touriño</ce:surname> </author> <author seq="2"> <ce:initials>R.</ce:initials> <ce:indexed-name>Inglott R.</ce:indexed-name> <ce:surname>Inglott</ce:surname> </author> <author seq="3"> <ce:initials>E.</ce:initials> <ce:indexed-name>Baena E.</ce:indexed-name> <ce:surname>Baena</ce:surname> </author> <author seq="4"> <ce:initials>J.</ce:initials> <ce:indexed-name>Fernandez J.</ce:indexed-name> <ce:surname>Fernández</ce:surname> </author> </ref-authors> <ref-sourcetitle>Guía de Intervención Familiar en la Esquizofrenia</ref-sourcetitle> <ref-publicationyear first="2004"/> <ref-text>Barcelona: Glosa</ref-text> </ref-info> <ref-fulltext>Touriño, R., Inglott, R., Baena, E., y Fernández, J. (2004). Guía de intervención familiar en la Esquizofrenia. Barcelona: Glosa.</ref-fulltext> </reference> <reference id="51"> <ref-info> <ref-title> <ref-titletext>Assertive community treatment of the mentally ill: Service model and effectiveness</ref-titletext> </ref-title> <refd-itemidlist> <itemid idtype="SGR">21644472723</itemid> </refd-itemidlist> <ref-authors> <author seq="1"> <ce:initials>A.</ce:initials> <ce:indexed-name>Udechuku A.</ce:indexed-name> <ce:surname>Udechuku</ce:surname> </author> <author seq="2"> <ce:initials>J.</ce:initials> <ce:indexed-name>Olver J.</ce:indexed-name> <ce:surname>Olver</ce:surname> </author> <author seq="3"> <ce:initials>K.</ce:initials> <ce:indexed-name>Hallam K.</ce:indexed-name> <ce:surname>Hallam</ce:surname> </author> <author seq="4"> <ce:initials>F.</ce:initials> <ce:indexed-name>Blyth F.</ce:indexed-name> <ce:surname>Blyth</ce:surname> </author> <author seq="5"> <ce:initials>M.</ce:initials> <ce:indexed-name>Leslie M.</ce:indexed-name> <ce:surname>Leslie</ce:surname> </author> <author seq="6"> <ce:initials>M.</ce:initials> <ce:indexed-name>Nasso M.</ce:indexed-name> <ce:surname>Nasso</ce:surname> </author> <author seq="7"> <ce:initials>P.</ce:initials> <ce:indexed-name>Schlesinger P.</ce:indexed-name> <ce:surname>Schlesinger</ce:surname> </author> <author seq="8"> <ce:initials>L.</ce:initials> <ce:indexed-name>Warren L.</ce:indexed-name> <ce:surname>Warren</ce:surname> </author> <author seq="9"> <ce:initials>M.</ce:initials> <ce:indexed-name>Turner M.</ce:indexed-name> <ce:surname>Turner</ce:surname> </author> <author seq="10"> <ce:initials>G.</ce:initials> <ce:indexed-name>Burrows G.</ce:indexed-name> <ce:surname>Burrows</ce:surname> </author> </ref-authors> <ref-sourcetitle>Australasian Psychiatry</ref-sourcetitle> <ref-publicationyear first="2005"/> <ref-volisspag> <voliss issue="2" volume="13"/> <pagerange first="129" last="134"/> </ref-volisspag> <ref-text>DOI 10.1111/j.1440-1665.2005.02175.x</ref-text> </ref-info> <ref-fulltext>Udechuku, A., Olver, J., Hallam, K., Blyth, F., Leslie, M., Nasso, M., Schlesinger, P., Warren L., Turner, M., y Burrows G. (2005). Assertive community treatment of the mentally ill: service model and effectiveness. Australasian Psychiatry, 13, 129-34. (Pubitemid 40936470)</ref-fulltext> </reference> <reference id="52"> <ref-info> <ref-title> <ref-titletext>Comparation of intensive and standard case management for patients with psychosis</ref-titletext> </ref-title> <refd-itemidlist> <itemid idtype="SGR">0007691190</itemid> </refd-itemidlist> <ref-sourcetitle>British Journal of Psychiatry</ref-sourcetitle> <ref-publicationyear first="1999"/> <ref-volisspag> <voliss volume="174"/> <pagerange first="74" last="78"/> </ref-volisspag> <ref-text>UK700 group</ref-text> </ref-info> <ref-fulltext>UK700 group (1999). Comparation of intensive and standard case management for patients with psychosis. British Journal of Psychiatry, 174, 74-78.</ref-fulltext> </reference> <reference id="53"> <ref-info> <ref-title> <ref-titletext>Cost-effectiviness of intensive v. standard case management for severe psychotic illness. Uk700 case management trial</ref-titletext> </ref-title> <refd-itemidlist> <itemid idtype="SGR">0034041184</itemid> </refd-itemidlist> <ref-sourcetitle>British Journal of Psychiatry</ref-sourcetitle> <ref-publicationyear first="2000"/> <ref-volisspag> <voliss volume="176"/> <pagerange first="537" last="543"/> </ref-volisspag> <ref-text>UK700 group</ref-text> </ref-info> <ref-fulltext>UK700 group (2000). Cost-effectiviness of intensive v. standard case management for severe psychotic illness. Uk700 case management trial. British Journal of Psychiatry, 176, 537-543.</ref-fulltext> </reference> <reference id="54"> <ref-info> <ref-title> <ref-titletext>Alternative to mental hospital treatment. II. Economic benefit-cost analysis</ref-titletext> </ref-title> <refd-itemidlist> <itemid idtype="SGR">0018893341</itemid> </refd-itemidlist> <ref-authors> <author seq="1"> <ce:initials>B.A.</ce:initials> <ce:indexed-name>Weisbrod B.A.</ce:indexed-name> <ce:surname>Weisbrod</ce:surname> </author> <author seq="2"> <ce:initials>M.A.</ce:initials> <ce:indexed-name>Test M.A.</ce:indexed-name> <ce:surname>Test</ce:surname> </author> <author seq="3"> <ce:initials>L.I.</ce:initials> <ce:indexed-name>Stein L.I.</ce:indexed-name> <ce:surname>Stein</ce:surname> </author> </ref-authors> <ref-sourcetitle>Archives of General Psychiatry</ref-sourcetitle> <ref-publicationyear first="1980"/> <ref-volisspag> <voliss issue="4" volume="37"/> <pagerange first="400" last="405"/> </ref-volisspag> </ref-info> <ref-fulltext>Weisbrod, B. A., Test, M. A., y Stein, L. I. (1980). Alternative to mental hospital treatment. II. Economic be-nefit-cost analysis. Archives of General Psychiatry, 37, 400-405. (Pubitemid 10100567)</ref-fulltext> </reference> <reference id="55"> <ref-info> <ref-title> <ref-titletext>A Meta-Analysis of the Effectiveness of Mental Health Case Management over 20 years</ref-titletext> </ref-title> <refd-itemidlist> <itemid idtype="SGR">0033783952</itemid> </refd-itemidlist> <ref-authors> <author seq="1"> <ce:initials>S.J.</ce:initials> <ce:indexed-name>Ziguras S.J.</ce:indexed-name> <ce:surname>Ziguras</ce:surname> </author> <author seq="2"> <ce:initials>G.W.</ce:initials> <ce:indexed-name>Stuart G.W.</ce:indexed-name> <ce:surname>Stuart</ce:surname> </author> </ref-authors> <ref-sourcetitle>Psychiatic Services</ref-sourcetitle> <ref-publicationyear first="2000"/> <ref-volisspag> <voliss volume="51"/> <pagerange first="1410" last="1422"/> </ref-volisspag> </ref-info> <ref-fulltext>Ziguras, S. J., y Stuart, G. W. (2000). A Meta-Analysis of the Effectiveness of Mental Health Case Management over 20 years. Psychiatic Services, 51, 1410-1422.</ref-fulltext> </reference> </bibliography>
      </tail>
    </bibrecord>
  </item>
</abstracts-retrieval-response>
